petstore_client_test/__init__.py
petstore_client_test/api_client.py
petstore_client_test/api_response.py
petstore_client_test/configuration.py
petstore_client_test/exceptions.py
petstore_client_test/py.typed
petstore_client_test/rest.py
petstore_client_test/api/__init__.py
petstore_client_test/api/pet_api.py
petstore_client_test/api/store_api.py
petstore_client_test/api/user_api.py
petstore_client_test/models/__init__.py
petstore_client_test/models/address.py
petstore_client_test/models/api_response.py
petstore_client_test/models/category.py
petstore_client_test/models/customer.py
petstore_client_test/models/order.py
petstore_client_test/models/pet.py
petstore_client_test/models/tag.py
petstore_client_test/models/user.py
petstore_client_test-1.0.0.dist-info/METADATA
petstore_client_test-1.0.0.dist-info/WHEEL
petstore_client_test-1.0.0.dist-info/top_level.txt
petstore_client_test-1.0.0.dist-info/RECORD
